nonebot_plugin_cloudsignx/__init__.py
nonebot_plugin_cloudsignx/config.py
nonebot_plugin_cloudsignx-2.1.2.dist-info/LICENSE
nonebot_plugin_cloudsignx-2.1.2.dist-info/METADATA
nonebot_plugin_cloudsignx-2.1.2.dist-info/WHEEL
nonebot_plugin_cloudsignx-2.1.2.dist-info/RECORD
